AVR/__init__.py
AVR/models.py
AVR/system.py
AVR/voiceModel.py
AVR-0.3.5.dist-info/METADATA
AVR-0.3.5.dist-info/WHEEL
AVR-0.3.5.dist-info/top_level.txt
AVR-0.3.5.dist-info/RECORD
