Metadata-Version: 2.1
Name: AVR
Version: 0.3.5
Summary: AVR is a voice anti-spoofing system that uses deep learning models to detect spoofed audio files.
Home-page: https://github.com/AshenPumpkin/AI-Voice-Recognition
Author: Ynon Friedman & Guy Ben Ari
Author-email: ynonfridman@gmail.com, Gbenari2@gmail.com
Classifier: Programming Language :: Python :: 3
Classifier: License :: OSI Approved :: MIT License
Classifier: Operating System :: OS Independent
Requires-Python: >=3.6
Requires-Dist: librosa >=0.10.1
Requires-Dist: matplotlib >=3.7.3
Requires-Dist: numpy >=1.24.0
Requires-Dist: pandas >=2.1.0
Requires-Dist: torch ==2.3.1
Requires-Dist: torchvision ==0.18.1
Requires-Dist: torchaudio ==2.3.1
Requires-Dist: scipy >=1.11.2
Requires-Dist: soundfile >=0.12.1
Requires-Dist: setuptools >=65.5.0
Requires-Dist: scikit-learn >=1.3.0
Requires-Dist: transformers >=4.33.2
Requires-Dist: huggingface-hub >=0.17.2
Requires-Dist: dill >=0.3.8
